README.md
setup.py
examples/__init__.py
examples/kmeans.py
examples/knn_classifier.py
examples/knn_regressor.py
examples/linear_regression.py
examples/logistic_regression.py
ravml/__init__.py
ravml/activations.py
ravml/config.py
ravml/kernels.py
ravml.egg-info/PKG-INFO
ravml.egg-info/SOURCES.txt
ravml.egg-info/dependency_links.txt
ravml.egg-info/requires.txt
ravml.egg-info/top_level.txt
ravml/base/__init__.py
ravml/cluster/__init__.py
ravml/linear/__init__.py
ravml/linear/perceptron.py
ravml/linear/linear_regression/__init__.py
ravml/linear/linear_regression/linear_regression.py
ravml/linear/logistic_regression/__init__.py
ravml/linear/logistic_regression/logistic_regression.py
ravml/neighbors/__init__.py
ravml/svm/__init__.py
ravml/svm/svm.py