Metadata-Version: 2.1
Name: ravml
Version: 0.5
Summary: UNKNOWN
Home-page: https://github.com/ravenprotocol/ravdl
Author: Raven Protocol
Author-email: kailash@ravenprotocol.com
License: MIT
Keywords: Ravml,machine learning library,algorithms
Platform: UNKNOWN
